{
  "functions": [
    {
      "complexity": 0,
      "file_name": "step2_review.py",
      "function_name": "clip_quality_score",
      "path": "step2_review.py"
    },
    {
      "complexity": 1,
      "file_name": "step2_review.py",
      "function_name": "_render_step2_controls",
      "path": "step2_review.py"
    },
    {
      "complexity": 1,
      "file_name": "step2_review.py",
      "function_name": "render_step2",
      "path": "step2_review.py"
    },
    {
      "complexity": 4,
      "file_name": "step2_review.py",
      "function_name": "_render_duration_and_clip_row",
      "path": "step2_review.py"
    },
    {
      "complexity": 4,
      "file_name": "step2_review.py",
      "function_name": "_render_period_expansions",
      "path": "step2_review.py"
    },
    {
      "complexity": 4,
      "file_name": "step2_review.py",
      "function_name": "_render_step2_content",
      "path": "step2_review.py"
    },
    {
      "complexity": 5,
      "file_name": "step2_review.py",
      "function_name": "_make_lazy_loader",
      "path": "step2_review.py"
    },
    {
      "complexity": 6,
      "file_name": "step2_review.py",
      "function_name": "_auto_deselect_duplicates",
      "path": "step2_review.py"
    },
    {
      "complexity": 10,
      "file_name": "step2_review.py",
      "function_name": "_render_step2_header",
      "path": "step2_review.py"
    },
    {
      "complexity": 12,
      "file_name": "step2_review.py",
      "function_name": "_render_selection_options",
      "path": "step2_review.py"
    }
  ],
  "targets": [
    "/Users/sam/Code/perso/immich-video-memory-generator/src/immich_memories/ui/pages/step2_review.py"
  ]
}